awx_plugins/credentials/aim.py
awx_plugins/credentials/aws_secretsmanager.py
awx_plugins/credentials/azure_kv.py
awx_plugins/credentials/centrify_vault.py
awx_plugins/credentials/conjur.py
awx_plugins/credentials/dsv.py
awx_plugins/credentials/github_app.py
awx_plugins/credentials/hashivault.py
awx_plugins/credentials/injectors.py
awx_plugins/credentials/plugin.py
awx_plugins/credentials/plugins.py
awx_plugins/credentials/py.typed
awx_plugins/credentials/tss.py
awx_plugins/inventory/plugins.py
awx_plugins/inventory/py.typed
awx_plugins_core-0.0.1a10.dist-info/LICENSE
awx_plugins_core-0.0.1a10.dist-info/METADATA
awx_plugins_core-0.0.1a10.dist-info/WHEEL
awx_plugins_core-0.0.1a10.dist-info/entry_points.txt
awx_plugins_core-0.0.1a10.dist-info/top_level.txt
awx_plugins_core-0.0.1a10.dist-info/RECORD
