Metadata-Version: 2.1
Name: awx-plugins-core
Version: 0.0.1a10
Summary: A temporary home for the essential AWX plugins
Author: Ansible maintainers and contributors
License: 
Project-URL: Homepage, https://docs.ansible.com
Project-URL: Chat: Discuss Forum, https://forum.ansible.com
Project-URL: Chat: Matrix, https://matrix.to/#/#awx:ansible.com
Project-URL: CI: GitHub, https://github.com/ansible/awx-plugins/actions/workflows/ci-cd.yml
Project-URL: Docs: RTD, https://awx-plugins-core.rtfd.io
Project-URL: GitHub: issues, https://github.com/ansible/awx-plugins/issues
Project-URL: GitHub: repo, https://github.com/ansible/awx-plugins
Keywords: Ansible,AWX
Classifier: Development Status :: 1 - Planning
Classifier: Environment :: Web Environment
Classifier: Framework :: Ansible
Classifier: Intended Audience :: System Administrators
Classifier: License :: OSI Approved :: Apache Software License
Classifier: Operating System :: POSIX :: Linux
Classifier: Programming Language :: Python :: 3
Classifier: Programming Language :: Python :: 3.11
Classifier: Programming Language :: Python :: 3.12
Classifier: Programming Language :: Python :: 3.13
Classifier: Topic :: System :: Systems Administration
Classifier: Typing :: Typed
Requires-Python: >=3.11
License-File: LICENSE
Provides-Extra: credentials-aim
Requires-Dist: awx-plugins.interfaces ; extra == 'credentials-aim'
Requires-Dist: requests ; extra == 'credentials-aim'
Provides-Extra: credentials-aws-secretsmanager-credential
Requires-Dist: awx-plugins.interfaces ; extra == 'credentials-aws-secretsmanager-credential'
Requires-Dist: boto3 ; extra == 'credentials-aws-secretsmanager-credential'
Provides-Extra: credentials-azure-kv
Requires-Dist: awx-plugins.interfaces ; extra == 'credentials-azure-kv'
Requires-Dist: azure-identity ; extra == 'credentials-azure-kv'
Requires-Dist: azure-keyvault ; extra == 'credentials-azure-kv'
Requires-Dist: msrestazure ; extra == 'credentials-azure-kv'
Provides-Extra: credentials-centrify-vault-kv
Requires-Dist: awx-plugins.interfaces ; extra == 'credentials-centrify-vault-kv'
Requires-Dist: requests ; extra == 'credentials-centrify-vault-kv'
Provides-Extra: credentials-conjur
Requires-Dist: awx-plugins.interfaces ; extra == 'credentials-conjur'
Requires-Dist: requests ; extra == 'credentials-conjur'
Provides-Extra: credentials-github-app
Requires-Dist: awx-plugins.interfaces ; extra == 'credentials-github-app'
Requires-Dist: PyGithub ; extra == 'credentials-github-app'
Provides-Extra: credentials-hashivault-kv
Requires-Dist: awx-plugins.interfaces ; extra == 'credentials-hashivault-kv'
Requires-Dist: requests ; extra == 'credentials-hashivault-kv'
Provides-Extra: credentials-hashivault-ssh
Requires-Dist: awx-plugins.interfaces ; extra == 'credentials-hashivault-ssh'
Requires-Dist: requests ; extra == 'credentials-hashivault-ssh'
Provides-Extra: credentials-thycotic-dsv
Requires-Dist: awx-plugins.interfaces ; extra == 'credentials-thycotic-dsv'
Requires-Dist: python-dsv-sdk >=1.0.4 ; extra == 'credentials-thycotic-dsv'
Provides-Extra: credentials-thycotic-tss
Requires-Dist: awx-plugins.interfaces ; extra == 'credentials-thycotic-tss'
Requires-Dist: python-tss-sdk >=1.2.1 ; extra == 'credentials-thycotic-tss'
Provides-Extra: inventory-azure-rm
Requires-Dist: awx-plugins.interfaces ; extra == 'inventory-azure-rm'
Requires-Dist: PyYAML ; extra == 'inventory-azure-rm'
Provides-Extra: inventory-constructed
Requires-Dist: awx-plugins.interfaces ; extra == 'inventory-constructed'
Requires-Dist: PyYAML ; extra == 'inventory-constructed'
Provides-Extra: inventory-controller
Requires-Dist: awx-plugins.interfaces ; extra == 'inventory-controller'
Requires-Dist: PyYAML ; extra == 'inventory-controller'
Provides-Extra: inventory-ec2
Requires-Dist: awx-plugins.interfaces ; extra == 'inventory-ec2'
Requires-Dist: PyYAML ; extra == 'inventory-ec2'
Provides-Extra: inventory-gce
Requires-Dist: awx-plugins.interfaces ; extra == 'inventory-gce'
Requires-Dist: PyYAML ; extra == 'inventory-gce'
Provides-Extra: inventory-insights
Requires-Dist: awx-plugins.interfaces ; extra == 'inventory-insights'
Requires-Dist: PyYAML ; extra == 'inventory-insights'
Provides-Extra: inventory-openshift-virtualization
Requires-Dist: awx-plugins.interfaces ; extra == 'inventory-openshift-virtualization'
Requires-Dist: PyYAML ; extra == 'inventory-openshift-virtualization'
Provides-Extra: inventory-openstack
Requires-Dist: awx-plugins.interfaces ; extra == 'inventory-openstack'
Requires-Dist: PyYAML ; extra == 'inventory-openstack'
Provides-Extra: inventory-rhv
Requires-Dist: awx-plugins.interfaces ; extra == 'inventory-rhv'
Requires-Dist: PyYAML ; extra == 'inventory-rhv'
Provides-Extra: inventory-satellite6
Requires-Dist: awx-plugins.interfaces ; extra == 'inventory-satellite6'
Requires-Dist: PyYAML ; extra == 'inventory-satellite6'
Provides-Extra: inventory-terraform
Requires-Dist: awx-plugins.interfaces ; extra == 'inventory-terraform'
Requires-Dist: PyYAML ; extra == 'inventory-terraform'
Provides-Extra: inventory-vmware
Requires-Dist: awx-plugins.interfaces ; extra == 'inventory-vmware'
Requires-Dist: PyYAML ; extra == 'inventory-vmware'
